helloworld-rayaq/__init__.py
helloworld-rayaq/helloworld.py
rayaq001/__init__.py
rayaq001/helloworld.py
rayaq001-0.0.1.dist-info/METADATA
rayaq001-0.0.1.dist-info/WHEEL
rayaq001-0.0.1.dist-info/top_level.txt
rayaq001-0.0.1.dist-info/RECORD
