Metadata-Version: 2.1
Name: rayaq001
Version: 0.0.1
Summary: Python Hello World Package
Home-page: UNKNOWN
Author: Rayaq Siddiqui
Author-email: rayaq05@hotmail.com
License: UNKNOWN
Keywords: python,first package
Platform: UNKNOWN
Classifier: Development Status :: 3 - Alpha
Classifier: Intended Audience :: Education
Classifier: Programming Language :: Python :: 2
Classifier: Programming Language :: Python :: 3
Classifier: Operating System :: MacOS :: MacOS X
Classifier: Operating System :: Microsoft :: Windows
